fluxem/__init__.py
fluxem/arithmetic/__init__.py
fluxem/arithmetic/extended_ops.py
fluxem/arithmetic/linear_encoder.py
fluxem/arithmetic/log_encoder.py
fluxem/arithmetic/unified.py
fluxem/backend/__init__.py
fluxem/backend/_jax.py
fluxem/backend/_mlx.py
fluxem/backend/_numpy.py
fluxem/core/__init__.py
fluxem/core/base.py
fluxem/core/unified.py
fluxem/domains/biology/__init__.py
fluxem/domains/biology/dna.py
fluxem/domains/biology/pathways.py
fluxem/domains/biology/protein.py
fluxem/domains/biology/taxonomy.py
fluxem/domains/chemistry/__init__.py
fluxem/domains/chemistry/bonds.py
fluxem/domains/chemistry/elements.py
fluxem/domains/chemistry/molecules.py
fluxem/domains/chemistry/reactions.py
fluxem/domains/data/__init__.py
fluxem/domains/data/arrays.py
fluxem/domains/data/records.py
fluxem/domains/geometry/__init__.py
fluxem/domains/geometry/points.py
fluxem/domains/geometry/shapes.py
fluxem/domains/geometry/transforms.py
fluxem/domains/geometry/vectors.py
fluxem/domains/graphs/__init__.py
fluxem/domains/graphs/graphs.py
fluxem/domains/graphs/paths.py
fluxem/domains/graphs/properties.py
fluxem/domains/logic/__init__.py
fluxem/domains/logic/predicates.py
fluxem/domains/logic/propositional.py
fluxem/domains/logic/types.py
fluxem/domains/math/__init__.py
fluxem/domains/math/arithmetic.py
fluxem/domains/math/complex.py
fluxem/domains/math/datetime_encoder.py
fluxem/domains/math/matrix.py
fluxem/domains/math/polynomial.py
fluxem/domains/math/rational.py
fluxem/domains/math/vector.py
fluxem/domains/music/__init__.py
fluxem/domains/music/atonal.py
fluxem/domains/number_theory/__init__.py
fluxem/domains/number_theory/divisibility.py
fluxem/domains/number_theory/integers.py
fluxem/domains/number_theory/modular.py
fluxem/domains/number_theory/primes.py
fluxem/domains/number_theory/rationals.py
fluxem/domains/physics/__init__.py
fluxem/domains/physics/constants.py
fluxem/domains/physics/dimensions.py
fluxem/domains/physics/units.py
fluxem/domains/sets/__init__.py
fluxem-1.0.1.dist-info/METADATA
fluxem-1.0.1.dist-info/WHEEL
fluxem-1.0.1.dist-info/licenses/LICENSE
fluxem-1.0.1.dist-info/RECORD
