Metadata-Version: 2.4
Name: fluxem
Version: 1.0.1
Summary: Algebraic embeddings for deterministic neural computation across scientific domains
Project-URL: Homepage, https://github.com/Hmbown/FluxEM
Project-URL: Repository, https://github.com/Hmbown/FluxEM
Project-URL: Documentation, https://github.com/Hmbown/FluxEM#readme
Author: Hunter Bown
License-Expression: MIT
License-File: LICENSE
Keywords: algebraic,biology,chemistry,embeddings,jax,machine-learning,mathematics,mlx,music-theory,neural-networks,physics
Classifier: Development Status :: 4 - Beta
Classifier: Intended Audience :: Science/Research
Classifier: License :: OSI Approved :: MIT License
Classifier: Programming Language :: Python :: 3.10
Classifier: Programming Language :: Python :: 3.11
Classifier: Programming Language :: Python :: 3.12
Classifier: Topic :: Scientific/Engineering :: Artificial Intelligence
Classifier: Topic :: Scientific/Engineering :: Bio-Informatics
Classifier: Topic :: Scientific/Engineering :: Chemistry
Classifier: Topic :: Scientific/Engineering :: Mathematics
Classifier: Topic :: Scientific/Engineering :: Physics
Requires-Python: >=3.10
Requires-Dist: numpy>=1.20.0
Provides-Extra: dev
Requires-Dist: black>=23.0.0; extra == 'dev'
Requires-Dist: pytest-cov>=4.1.0; extra == 'dev'
Requires-Dist: pytest>=7.4.0; extra == 'dev'
Requires-Dist: ruff>=0.1.0; extra == 'dev'
Provides-Extra: full-jax
Requires-Dist: datasets>=2.10.0; extra == 'full-jax'
Requires-Dist: jax>=0.4.20; extra == 'full-jax'
Requires-Dist: jaxlib>=0.4.20; extra == 'full-jax'
Requires-Dist: transformers>=4.30.0; extra == 'full-jax'
Provides-Extra: full-mlx
Requires-Dist: datasets>=2.10.0; extra == 'full-mlx'
Requires-Dist: mlx>=0.4.0; extra == 'full-mlx'
Requires-Dist: transformers>=4.30.0; extra == 'full-mlx'
Provides-Extra: huggingface
Requires-Dist: datasets>=2.10.0; extra == 'huggingface'
Requires-Dist: transformers>=4.30.0; extra == 'huggingface'
Provides-Extra: jax
Requires-Dist: jax>=0.4.20; extra == 'jax'
Requires-Dist: jaxlib>=0.4.20; extra == 'jax'
Provides-Extra: mlx
Requires-Dist: mlx>=0.4.0; extra == 'mlx'
